{"cameraMode":{"drawMode":0,"name":"Shaded","section":"Shading Mode"},"sceneLighting":true,"audioPlay":false,"sceneViewState":{"showFog":true,"showMaterialUpdate":false,"showSkybox":true,"showFlares":true,"showImageEffects":true,"showParticleSystems":true},"in2DMode":false,"pivot":{"x":-10.63187026977539,"y":1.8687565326690674,"z":0.19488728046417237},"rotation":{"x":-0.17050038278102876,"y":0.6298734545707703,"z":-0.1443658173084259,"w":-0.7438815832138062},"size":6.333799839019775,"orthographic":false}